pythumbnailer/__init__.py
pythumbnailer/clean.py
pythumbnailer/prepare.py
pythumbnailer/pypublish.py
pythumbnailer/utils.py
pythumbnailer/static/gpx/multiple.js
pythumbnailer/static/gpx/style.css
pythumbnailer/static/lib/d3@4.13.0.min.js
pythumbnailer/static/lib/d3@5.16.0.min.js
pythumbnailer/static/lib/leaflet-elevation@0.3.9.min.css
pythumbnailer/static/lib/leaflet-elevation@0.3.9.min.js
pythumbnailer/static/lib/leaflet-elevation@1.3.4.min.css
pythumbnailer/static/lib/leaflet-elevation@1.3.4.min.js
pythumbnailer/static/lib/leaflet-gpx@1.4.0.min.js
pythumbnailer/static/lib/leaflet-gpx@1.5.0.min.js
pythumbnailer/static/lib/leaflet@1.3.2.css
pythumbnailer/static/lib/leaflet@1.3.2.min.js
pythumbnailer/static/lib/leaflet@1.6.0.css
pythumbnailer/static/lib/leaflet@1.6.0.min.js
pythumbnailer/static/lib/images/README.md
pythumbnailer/static/lib/images/default-pin.end.png
pythumbnailer/static/lib/images/default-pin.start.png
pythumbnailer/static/lib/images/default-pin.waypoint.png
pythumbnailer/static/lib/images/pin-shadow.png
pythumbnailer/templates/photo-album.html
pythumbnailer/templates/play-circle-regular.128.png
pythumbnailer/templates/play-circle-regular.256.png
pythumbnailer/templates/play-circle-regular.svg
pythumbnailer/templates/tracks.html
pythumbnailer/thumbnail/__init__.py
pythumbnailer/thumbnail/image.py
pythumbnailer/thumbnail/video.py
pythumbnailer-0.4.2.dist-info/LICENSE
pythumbnailer-0.4.2.dist-info/METADATA
pythumbnailer-0.4.2.dist-info/WHEEL
pythumbnailer-0.4.2.dist-info/entry_points.txt
pythumbnailer-0.4.2.dist-info/top_level.txt
pythumbnailer-0.4.2.dist-info/RECORD
