Metadata-Version: 2.1
Name: pythumbnailer
Version: 0.4.2
Summary: Create static HTML galleries with thumbnails
Home-page: https://gitlab.com/somini/pythumbnailer/
Author: somini
Author-email: dev@somini.xyz
License: UNKNOWN
Platform: UNKNOWN
Classifier: Environment :: Console
Classifier: Environment :: Web Environment
Classifier: License :: OSI Approved :: GNU General Public License v3 or later (GPLv3+)
Requires-Python: >=3.8
Requires-Dist: jinja2
Requires-Dist: pillow
Requires-Dist: argparse-utils
